LICENSE
setup.py
hanime/__init__.py
hanime/image.py
hanime/search.py
hanime/user.py
hanime/video.py
hanime.egg-info/PKG-INFO
hanime.egg-info/SOURCES.txt
hanime.egg-info/dependency_links.txt
hanime.egg-info/top_level.txt