Metadata-Version: 2.1
Name: hanime
Version: 1.0.1
Summary: A simple Python wrapper for interacting with Hanime's API.
Home-page: https://github.com/lolpuud/hanime
Author: dancers.
Author-email: bio@fbi.ac
Classifier: Development Status :: 5 - Production/Stable
Classifier: Intended Audience :: Developers
Classifier: License :: OSI Approved :: MIT License
Classifier: Programming Language :: Python :: 3
Classifier: Programming Language :: Python :: 3.6
Classifier: Programming Language :: Python :: 3.7
Classifier: Programming Language :: Python :: 3.8
Classifier: Programming Language :: Python :: 3.9
License-File: LICENSE
